pyemd_rs-0.1.3.dist-info/METADATA
pyemd_rs-0.1.3.dist-info/WHEEL
pyemd_rs-0.1.3.dist-info/licenses/LICENSE
pyemd_rs.libs/libgcc_s-98a1ef30.so.1
pyemd_rs/__init__.py
pyemd_rs/_pyemd_rs.cpython-313-x86_64-linux-musl.so
pyemd_rs/_pyemd_rs.pyi
pyemd_rs/_testing.py
pyemd_rs/emd.py
pyemd_rs/py.typed
pyemd_rs-0.1.3.dist-info/RECORD
