Metadata-Version: 2.4
Name: pyemd-rs
Version: 0.1.3
Classifier: Programming Language :: Python :: Implementation :: CPython
Classifier: Programming Language :: Python :: Implementation :: PyPy
Classifier: Programming Language :: Rust
Requires-Dist: numpy>1.24
License-File: LICENSE
Requires-Python: >=3.9
